<?xml version="1.0" encoding="utf-8"?>
<!DOCTYPE hibernate-mapping PUBLIC "-//Hibernate/Hibernate Mapping DTD 3.0//EN"
"http://hibernate.sourceforge.net/hibernate-mapping-3.0.dtd">
<!-- Mapping file autogenerated by MyEclipse Persistence Tools -->
<hibernate-mapping>
	<union-subclass name="net.yasion.common.model.TbRole" extends="net.yasion.common.model.BaseModel" table="tb_role">
		<property name="name" type="java.lang.String">
			<column name="name" length="60" />
		</property>
		<property name="code" type="java.lang.String">
			<column name="code" length="60" />
		</property>
		<property name="descr" type="java.lang.String">
			<column name="descr" />
		</property>
		<property name="disable" type="java.lang.String">
			<column name="disable" length="1" />
		</property>
	</union-subclass>
</hibernate-mapping>